{
  "status": 200,
  "data": {
    "hash": "2b3544a99de605698407030f7921c43609c158e3",
    "date": "2020-10-05T00:00:00Z",
    "featured": {
      "name": "Featured",
      "entries": [
        {
          "regularPrice": 2000,
          "finalPrice": 2000,
          "bundle": null,
          "banner": {
            "value": "Selectable Styles!",
            "backendValue": "SelectableStyles"
          },
          "giftable": true,
          "refundable": true,
          "sortPriority": -4,
          "categories": [
            "Panel 2"
          ],
          "devName": "[VIRTUAL]1 x Raptor, 1 x Raptor Satchel for 2000 MtxCurrency",
          "offerId": "v2:/325babceb5da51bd7d755c8cb372dccaa07011071d435ad4b8a3f8e1fbc6c4e7",
          "displayAssetPath": "FortniteGame/Content/Catalog/DisplayAssets/DA_Featured_SMaleHID031",
          "newDisplayAssetPath": "FortniteGame/Content/Catalog/NewDisplayAssets/DAv2_CID_031_M_Retro",
          "items": [
            {
              "id": "CID_031_Athena_Commando_M_Retro",
              "name": "Raptor",
              "description": "Royale Air Force test pilot.",
              "type": {
                "value": "outfit",
                "displayValue": "Outfit",
                "backendValue": "AthenaCharacter"
              },
              "rarity": {
                "value": "legendary",
                "displayValue": "Legendary",
                "backendValue": "EFortRarity::Legendary"
              },
              "series": null,
              "set": null,
              "introduction": {
                "chapter": "1",
                "season": "1",
                "text": "Introduced in Chapter 1, Season 1.",
                "backendValue": 1
              },
              "images": {
                "smallIcon": "https://fortnite-api.com/images/cosmetics/br/cid_031_athena_commando_m_retro/smallicon.png",
                "icon": "https://fortnite-api.com/images/cosmetics/br/cid_031_athena_commando_m_retro/icon.png",
                "featured": "https://fortnite-api.com/images/cosmetics/br/cid_031_athena_commando_m_retro/featured.png",
                "other": null
              },
              "variants": [
                {
                  "channel": "Material",
                  "type": "STYLE",
                  "options": [
                    {
                      "tag": "Mat1",
                      "name": "DEFAULT",
                      "unlockRequirements": null,
                      "image": "https://fortnite-api.com/images/cosmetics/br/cid_031_athena_commando_m_retro/variants/material/mat1.png"
                    },
                    {
                      "tag": "Mat2",
                      "name": "GLOW",
                      "unlockRequirements": null,
                      "image": "https://fortnite-api.com/images/cosmetics/br/cid_031_athena_commando_m_retro/variants/material/mat2.png"
                    }
                  ]
                }
              ],
              "gameplayTags": [
                "Cosmetics.Source.ItemShop",
                "Cosmetics.UserFacingFlags.HasVariants",
                "Cosmetics.Filter.Season.1"
              ],
              "showcaseVideo": "4owEW4-8h74",
              "displayAssetPath": "FortniteGame/Content/Catalog/DisplayAssets/DA_Featured_SMaleHID031",
              "definitionPath": "FortniteGame/Content/Athena/Heroes/HID_031_Athena_Commando_M_Retro",
              "path": "FortniteGame/Content/Athena/Items/Cosmetics/Characters/CID_031_Athena_Commando_M_Retro",
              "added": "2019-11-20T12:50:30Z",
              "shopHistory": [
                "2018-01-14T00:00:00Z",
                "2018-01-15T00:00:00Z",
                "2018-01-16T00:00:00Z",
                "2018-01-17T00:00:00Z",
                "2018-01-18T00:00:00Z",
                "2018-01-19T00:00:00Z",
                "2018-01-20T00:00:00Z",
                "2018-02-07T00:00:00Z",
                "2018-02-08T00:00:00Z",
                "2018-03-07T00:00:00Z",
                "2018-03-08T00:00:00Z",
                "2018-04-04T00:00:00Z",
                "2018-06-14T00:00:00Z",
                "2018-07-18T00:00:00Z",
                "2018-08-22T00:00:00Z",
                "2018-10-04T00:00:00Z",
                "2018-11-22T00:00:00Z",
                "2019-01-15T00:00:00Z",
                "2019-03-11T00:00:00Z",
                "2019-04-06T00:00:00Z",
                "2019-04-25T00:00:00Z",
                "2019-05-12T00:00:00Z",
                "2019-05-13T00:00:00Z",
                "2019-06-27T00:00:00Z",
                "2019-08-14T00:00:00Z",
                "2019-09-15T00:00:00Z",
                "2019-10-29T00:00:00Z",
                "2019-12-03T00:00:00Z",
                "2020-01-08T00:00:00Z",
                "2020-02-29T00:00:00Z",
                "2020-04-01T00:00:00Z",
                "2020-05-05T00:00:00Z",
                "2020-05-30T00:00:00Z",
                "2020-06-29T00:00:00Z",
                "2020-07-29T00:00:00Z",
                "2020-09-01T00:00:00Z",
                "2020-10-05T00:00:00Z"
              ]
            },
            {
              "id": "BID_005_Raptor",
              "name": "Raptor Satchel",
              "description": "Royale Air Force standard issue.",
              "type": {
                "value": "backpack",
                "displayValue": "Back Bling",
                "backendValue": "AthenaBackpack"
              },
              "rarity": {
                "value": "legendary",
                "displayValue": "Legendary",
                "backendValue": "EFortRarity::Legendary"
              },
              "series": null,
              "set": null,
              "introduction": {
                "chapter": "1",
                "season": "3",
                "text": "Introduced in Chapter 1, Season 3.",
                "backendValue": 3
              },
              "images": {
                "smallIcon": "https://fortnite-api.com/images/cosmetics/br/bid_005_raptor/smallicon.png",
                "icon": "https://fortnite-api.com/images/cosmetics/br/bid_005_raptor/icon.png",
                "featured": null,
                "other": null
              },
              "variants": null,
              "gameplayTags": [
                "Cosmetics.Source.ItemShop",
                "Cosmetics.Filter.Season.3"
              ],
              "showcaseVideo": null,
              "displayAssetPath": null,
              "definitionPath": null,
              "path": "FortniteGame/Content/Athena/Items/Cosmetics/Backpacks/BID_005_Raptor",
              "added": "2019-11-20T12:48:04Z",
              "shopHistory": [
                "2020-05-05T00:00:00Z",
                "2020-05-30T00:00:00Z",
                "2020-06-29T00:00:00Z",
                "2020-07-29T00:00:00Z",
                "2020-09-01T00:00:00Z",
                "2020-10-05T00:00:00Z"
              ]
            }
          ]
        },
        {
          "regularPrice": 1500,
          "finalPrice": 1500,
          "bundle": null,
          "banner": null,
          "giftable": true,
          "refundable": true,
          "sortPriority": -9,
          "categories": [
            "Panel 4"
          ],
          "devName": "[VIRTUAL]1 x Big Mouth, 1 x Council of Frogs for 1500 MtxCurrency",
          "offerId": "v2:/7f677657c674018106985fae505bd6980159cbace45b226ea845550dffcbb21a",
          "displayAssetPath": "FortniteGame/Content/Catalog/DisplayAssets/DA_Featured_CID_597_Athena_Commando_M_Freak",
          "newDisplayAssetPath": "FortniteGame/Content/Catalog/NewDisplayAssets/DAv2_CID_597M_Freak",
          "items": [
            {
              "id": "CID_597_Athena_Commando_M_Freak",
              "name": "Big Mouth",
              "description": "Seeking victory, breath mints, and souls.",
              "type": {
                "value": "outfit",
                "displayValue": "Outfit",
                "backendValue": "AthenaCharacter"
              },
              "rarity": {
                "value": "epic",
                "displayValue": "Epic",
                "backendValue": "EFortRarity::Epic"
              },
              "series": null,
              "set": {
                "value": "Fearsome Freaks",
                "text": "Part of the Fearsome Freaks set.",
                "backendValue": "FrighteningOddity"
              },
              "introduction": {
                "chapter": "2",
                "season": "1",
                "text": "Introduced in Chapter 2, Season 1.",
                "backendValue": 11
              },
              "images": {
                "smallIcon": "https://fortnite-api.com/images/cosmetics/br/cid_597_athena_commando_m_freak/smallicon.png",
                "icon": "https://fortnite-api.com/images/cosmetics/br/cid_597_athena_commando_m_freak/icon.png",
                "featured": "https://fortnite-api.com/images/cosmetics/br/cid_597_athena_commando_m_freak/featured.png",
                "other": null
              },
              "variants": null,
              "gameplayTags": [
                "Cosmetics.Source.ItemShop",
                "Cosmetics.Set.FrighteningOddity",
                "Cosmetics.Filter.Season.11",
                "Phoebe.Cosmetic.Minus.Zone2"
              ],
              "showcaseVideo": "8jXoCyP5vEI",
              "displayAssetPath": "FortniteGame/Content/Catalog/DisplayAssets/DA_Featured_CID_597_Athena_Commando_M_Freak",
              "definitionPath": "FortniteGame/Content/Athena/Heroes/HID_597_Athena_Commando_M_Freak",
              "path": "FortniteGame/Content/Athena/Items/Cosmetics/Characters/CID_597_Athena_Commando_M_Freak",
              "added": "2019-11-20T12:51:17Z",
              "shopHistory": [
                "2019-10-28T00:00:00Z",
                "2019-11-04T00:00:00Z",
                "2020-10-03T00:00:00Z",
                "2020-10-04T00:00:00Z",
                "2020-10-05T00:00:00Z"
              ]
            },
            {
              "id": "BID_392_Freak",
              "name": "Council of Frogs",
              "description": "Grant us wisdom.",
              "type": {
                "value": "backpack",
                "displayValue": "Back Bling",
                "backendValue": "AthenaBackpack"
              },
              "rarity": {
                "value": "epic",
                "displayValue": "Epic",
                "backendValue": "EFortRarity::Epic"
              },
              "series": null,
              "set": {
                "value": "Fearsome Freaks",
                "text": "Part of the Fearsome Freaks set.",
                "backendValue": "FrighteningOddity"
              },
              "introduction": {
                "chapter": "2",
                "season": "1",
                "text": "Introduced in Chapter 2, Season 1.",
                "backendValue": 11
              },
              "images": {
                "smallIcon": "https://fortnite-api.com/images/cosmetics/br/bid_392_freak/smallicon.png",
                "icon": "https://fortnite-api.com/images/cosmetics/br/bid_392_freak/icon.png",
                "featured": null,
                "other": null
              },
              "variants": null,
              "gameplayTags": [
                "Cosmetics.Source.ItemShop",
                "Cosmetics.Set.FrighteningOddity",
                "Cosmetics.Filter.Season.11"
              ],
              "showcaseVideo": null,
              "displayAssetPath": null,
              "definitionPath": null,
              "path": "FortniteGame/Content/Athena/Items/Cosmetics/Backpacks/BID_392_Freak",
              "added": "2019-11-20T12:51:14Z",
              "shopHistory": [
                "2020-10-03T00:00:00Z",
                "2020-10-04T00:00:00Z",
                "2020-10-05T00:00:00Z"
              ]
            }
          ]
        },
        {
          "regularPrice": 1500,
          "finalPrice": 1500,
          "bundle": null,
          "banner": null,
          "giftable": true,
          "refundable": true,
          "sortPriority": -7,
          "categories": [
            "Panel 3"
          ],
          "devName": "[VIRTUAL]1 x Delirium, 1 x Illusion Rune for 1500 MtxCurrency",
          "offerId": "v2:/e7d0a2e641ee9feea80b5b3dbfb61c39f826f66aa5b93bc544c769c9910f8937",
          "displayAssetPath": "FortniteGame/Content/Catalog/DisplayAssets/DA_Featured_CID_588_Athena_Commando_M_GoatRobe",
          "newDisplayAssetPath": "FortniteGame/Content/Catalog/NewDisplayAssets/DAv2_CID_588_M_Goatrobe",
          "items": [
            {
              "id": "CID_588_Athena_Commando_M_GoatRobe",
              "name": "Delirium",
              "description": "Don't worry, it's only a nightmare...",
              "type": {
                "value": "outfit",
                "displayValue": "Outfit",
                "backendValue": "AthenaCharacter"
              },
              "rarity": {
                "value": "epic",
                "displayValue": "Epic",
                "backendValue": "EFortRarity::Epic"
              },
              "series": null,
              "set": {
                "value": "Arcane Arts",
                "text": "Part of the Arcane Arts set.",
                "backendValue": "Witch"
              },
              "introduction": {
                "chapter": "2",
                "season": "1",
                "text": "Introduced in Chapter 2, Season 1.",
                "backendValue": 11
              },
              "images": {
                "smallIcon": "https://fortnite-api.com/images/cosmetics/br/cid_588_athena_commando_m_goatrobe/smallicon.png",
                "icon": "https://fortnite-api.com/images/cosmetics/br/cid_588_athena_commando_m_goatrobe/icon.png",
                "featured": "https://fortnite-api.com/images/cosmetics/br/cid_588_athena_commando_m_goatrobe/featured.png",
                "other": null
              },
              "variants": null,
              "gameplayTags": [
                "Cosmetics.Source.ItemShop",
                "Cosmetics.Set.Witch",
                "Cosmetics.Filter.Season.11"
              ],
              "showcaseVideo": "BgebMzIJQVY",
              "displayAssetPath": "FortniteGame/Content/Catalog/DisplayAssets/DA_Featured_CID_588_Athena_Commando_M_GoatRobe",
              "definitionPath": "FortniteGame/Content/Athena/Heroes/HID_588_Athena_Commando_M_GoatRobe",
              "path": "FortniteGame/Content/Athena/Items/Cosmetics/Characters/CID_588_Athena_Commando_M_GoatRobe",
              "added": "2019-11-20T12:51:16Z",
              "shopHistory": [
                "2019-10-26T00:00:00Z",
                "2019-10-27T00:00:00Z",
                "2019-11-03T00:00:00Z",
                "2019-11-04T00:00:00Z",
                "2020-10-03T00:00:00Z",
                "2020-10-04T00:00:00Z",
                "2020-10-05T00:00:00Z"
              ]
            },
            {
              "id": "BID_389_GoatRobe",
              "name": "Illusion Rune",
              "description": "Make them see.",
              "type": {
                "value": "backpack",
                "displayValue": "Back Bling",
                "backendValue": "AthenaBackpack"
              },
              "rarity": {
                "value": "epic",
                "displayValue": "Epic",
                "backendValue": "EFortRarity::Epic"
              },
              "series": null,
              "set": {
                "value": "Arcane Arts",
                "text": "Part of the Arcane Arts set.",
                "backendValue": "Witch"
              },
              "introduction": {
                "chapter": "2",
                "season": "1",
                "text": "Introduced in Chapter 2, Season 1.",
                "backendValue": 11
              },
              "images": {
                "smallIcon": "https://fortnite-api.com/images/cosmetics/br/bid_389_goatrobe/smallicon.png",
                "icon": "https://fortnite-api.com/images/cosmetics/br/bid_389_goatrobe/icon.png",
                "featured": null,
                "other": null
              },
              "variants": null,
              "gameplayTags": [
                "Cosmetics.Source.ItemShop",
                "Cosmetics.Set.Witch",
                "Cosmetics.Filter.Season.11"
              ],
              "showcaseVideo": null,
              "displayAssetPath": null,
              "definitionPath": null,
              "path": "FortniteGame/Content/Athena/Items/Cosmetics/Backpacks/BID_389_GoatRobe",
              "added": "2019-11-20T12:51:14Z",
              "shopHistory": [
                "2020-10-03T00:00:00Z",
                "2020-10-04T00:00:00Z",
                "2020-10-05T00:00:00Z"
              ]
            }
          ]
        },
        {
          "regularPrice": 1500,
          "finalPrice": 1500,
          "bundle": null,
          "banner": null,
          "giftable": true,
          "refundable": true,
          "sortPriority": -3,
          "categories": [
            "Panel 2"
          ],
          "devName": "[VIRTUAL]1 x Teef, 1 x Nosh for 1500 MtxCurrency",
          "offerId": "v2:/513e3d54d0c419bf87e6f47e42bb0e9d6beb48029713663d3df8502629a417de",
          "displayAssetPath": "FortniteGame/Content/Catalog/DisplayAssets/DA_Featured_CID_584_Athena_Commando_M_Nosh",
          "newDisplayAssetPath": "FortniteGame/Content/Catalog/NewDisplayAssets/DAv2_CID_584_M_Nosh",
          "items": [
            {
              "id": "CID_584_Athena_Commando_M_Nosh",
              "name": "Teef",
              "description": "Life's chewy when you're born to chomp.",
              "type": {
                "value": "outfit",
                "displayValue": "Outfit",
                "backendValue": "AthenaCharacter"
              },
              "rarity": {
                "value": "epic",
                "displayValue": "Epic",
                "backendValue": "EFortRarity::Epic"
              },
              "series": null,
              "set": {
                "value": "Final Reckoning",
                "text": "Part of the Final Reckoning set.",
                "backendValue": "GardenBones"
              },
              "introduction": {
                "chapter": "2",
                "season": "1",
                "text": "Introduced in Chapter 2, Season 1.",
                "backendValue": 11
              },
              "images": {
                "smallIcon": "https://fortnite-api.com/images/cosmetics/br/cid_584_athena_commando_m_nosh/smallicon.png",
                "icon": "https://fortnite-api.com/images/cosmetics/br/cid_584_athena_commando_m_nosh/icon.png",
                "featured": "https://fortnite-api.com/images/cosmetics/br/cid_584_athena_commando_m_nosh/featured.png",
                "other": null
              },
              "variants": null,
              "gameplayTags": [
                "Cosmetics.Source.ItemShop",
                "Cosmetics.Set.GardenBones",
                "Cosmetics.Filter.Season.11"
              ],
              "showcaseVideo": "Sd4GesTDswQ",
              "displayAssetPath": "FortniteGame/Content/Catalog/DisplayAssets/DA_Featured_CID_584_Athena_Commando_M_Nosh",
              "definitionPath": "FortniteGame/Content/Athena/Heroes/HID_584_Athena_Commando_M_Nosh",
              "path": "FortniteGame/Content/Athena/Items/Cosmetics/Characters/CID_584_Athena_Commando_M_Nosh",
              "added": "2019-11-20T12:51:16Z",
              "shopHistory": [
                "2019-10-24T00:00:00Z",
                "2019-11-01T00:00:00Z",
                "2020-10-04T00:00:00Z",
                "2020-10-05T00:00:00Z"
              ]
            },
            {
              "id": "BID_385_Nosh",
              "name": "Nosh",
              "description": "The snack that bites back.",
              "type": {
                "value": "backpack",
                "displayValue": "Back Bling",
                "backendValue": "AthenaBackpack"
              },
              "rarity": {
                "value": "epic",
                "displayValue": "Epic",
                "backendValue": "EFortRarity::Epic"
              },
              "series": null,
              "set": {
                "value": "Final Reckoning",
                "text": "Part of the Final Reckoning set.",
                "backendValue": "GardenBones"
              },
              "introduction": {
                "chapter": "2",
                "season": "1",
                "text": "Introduced in Chapter 2, Season 1.",
                "backendValue": 11
              },
              "images": {
                "smallIcon": "https://fortnite-api.com/images/cosmetics/br/bid_385_nosh/smallicon.png",
                "icon": "https://fortnite-api.com/images/cosmetics/br/bid_385_nosh/icon.png",
                "featured": null,
                "other": null
              },
              "variants": null,
              "gameplayTags": [
                "Cosmetics.Source.ItemShop",
                "Cosmetics.Set.GardenBones",
                "Cosmetics.Filter.Season.11"
              ],
              "showcaseVideo": null,
              "displayAssetPath": null,
              "definitionPath": null,
              "path": "FortniteGame/Content/Athena/Items/Cosmetics/Backpacks/BID_385_Nosh",
              "added": "2019-11-20T12:51:15Z",
              "shopHistory": [
                "2020-10-04T00:00:00Z",
                "2020-10-05T00:00:00Z"
              ]
            }
          ]
        },
        {
          "regularPrice": 600,
          "finalPrice": 600,
          "bundle": null,
          "banner": {
            "value": "Collect the Set!",
            "backendValue": "CollectTheSet"
          },
          "giftable": true,
          "refundable": true,
          "sortPriority": -5,
          "categories": [
            "Panel 2"
          ],
          "devName": "[VIRTUAL]1 x Back-o-lantern for 600 MtxCurrency",
          "offerId": "v2:/15d624620964e726647f634ebc5597ffef502dd08509bf22e28a3e42f26ab73e",
          "displayAssetPath": "FortniteGame/Content/Catalog/DisplayAssets/DA_Featured_BID_396_RaptorGlow",
          "newDisplayAssetPath": "FortniteGame/Content/Catalog/NewDisplayAssets/DAv2_BID_396_RaptorGlow",
          "items": [
            {
              "id": "BID_396_RaptorGlow",
              "name": "Back-o-lantern",
              "description": "Share a spooky smile.",
              "type": {
                "value": "backpack",
                "displayValue": "Back Bling",
                "backendValue": "AthenaBackpack"
              },
              "rarity": {
                "value": "epic",
                "displayValue": "Epic",
                "backendValue": "EFortRarity::Epic"
              },
              "series": null,
              "set": null,
              "introduction": {
                "chapter": "2",
                "season": "1",
                "text": "Introduced in Chapter 2, Season 1.",
                "backendValue": 11
              },
              "images": {
                "smallIcon": "https://fortnite-api.com/images/cosmetics/br/bid_396_raptorglow/smallicon.png",
                "icon": "https://fortnite-api.com/images/cosmetics/br/bid_396_raptorglow/icon.png",
                "featured": "https://fortnite-api.com/images/cosmetics/br/bid_396_raptorglow/featured.png",
                "other": null
              },
              "variants": null,
              "gameplayTags": [
                "Cosmetics.Source.ItemShop",
                "Cosmetics.Filter.Season.11"
              ],
              "showcaseVideo": "oEiaeumy8AM",
              "displayAssetPath": "FortniteGame/Content/Catalog/DisplayAssets/DA_Featured_BID_396_RaptorGlow",
              "definitionPath": null,
              "path": "FortniteGame/Content/Athena/Items/Cosmetics/Backpacks/BID_396_RaptorGlow",
              "added": "2019-11-20T12:51:15Z",
              "shopHistory": [
                "2019-10-29T00:00:00Z",
                "2019-11-01T00:00:00Z",
                "2020-10-05T00:00:00Z"
              ]
            }
          ]
        },
        {
          "regularPrice": 1200,
          "finalPrice": 1200,
          "bundle": null,
          "banner": null,
          "giftable": true,
          "refundable": true,
          "sortPriority": -1,
          "categories": [
            "Panel 1"
          ],
          "devName": "[VIRTUAL]1 x Jawbreaker, 1 x Containment Unit for 1200 MtxCurrency",
          "offerId": "v2:/43f8544511433322e6541f749c64aca1576c6ed2868971a6250951457f969a15",
          "displayAssetPath": "FortniteGame/Content/Catalog/DisplayAssets/DA_Featured_CID_583_Athena_Commando_F_NoshHunter",
          "newDisplayAssetPath": "FortniteGame/Content/Catalog/NewDisplayAssets/DAv2_CID_583_F_NoshHunter",
          "items": [
            {
              "id": "CID_583_Athena_Commando_F_NoshHunter",
              "name": "Jawbreaker",
              "description": "She's playing the most delicious game.",
              "type": {
                "value": "outfit",
                "displayValue": "Outfit",
                "backendValue": "AthenaCharacter"
              },
              "rarity": {
                "value": "rare",
                "displayValue": "Rare",
                "backendValue": "EFortRarity::Rare"
              },
              "series": null,
              "set": {
                "value": "Final Reckoning",
                "text": "Part of the Final Reckoning set.",
                "backendValue": "GardenBones"
              },
              "introduction": {
                "chapter": "2",
                "season": "1",
                "text": "Introduced in Chapter 2, Season 1.",
                "backendValue": 11
              },
              "images": {
                "smallIcon": "https://fortnite-api.com/images/cosmetics/br/cid_583_athena_commando_f_noshhunter/smallicon.png",
                "icon": "https://fortnite-api.com/images/cosmetics/br/cid_583_athena_commando_f_noshhunter/icon.png",
                "featured": "https://fortnite-api.com/images/cosmetics/br/cid_583_athena_commando_f_noshhunter/featured.png",
                "other": null
              },
              "variants": null,
              "gameplayTags": [
                "Cosmetics.Source.ItemShop",
                "Cosmetics.Set.GardenBones",
                "Cosmetics.Filter.Season.11"
              ],
              "showcaseVideo": "zfsVWg0eJq8",
              "displayAssetPath": "FortniteGame/Content/Catalog/DisplayAssets/DA_Featured_CID_583_Athena_Commando_F_NoshHunter",
              "definitionPath": "FortniteGame/Content/Athena/Heroes/HID_583_Athena_Commando_F_NoshHunter",
              "path": "FortniteGame/Content/Athena/Items/Cosmetics/Characters/CID_583_Athena_Commando_F_NoshHunter",
              "added": "2019-11-20T12:51:16Z",
              "shopHistory": [
                "2019-10-24T00:00:00Z",
                "2019-11-01T00:00:00Z",
                "2020-10-04T00:00:00Z",
                "2020-10-05T00:00:00Z"
              ]
            },
            {
              "id": "BID_384_NoshHunter",
              "name": "Containment Unit",
              "description": "Perfectly stabilized for Nosh entrapment.",
              "type": {
                "value": "backpack",
                "displayValue": "Back Bling",
                "backendValue": "AthenaBackpack"
              },
              "rarity": {
                "value": "rare",
                "displayValue": "Rare",
                "backendValue": "EFortRarity::Rare"
              },
              "series": null,
              "set": {
                "value": "Final Reckoning",
                "text": "Part of the Final Reckoning set.",
                "backendValue": "GardenBones"
              },
              "introduction": {
                "chapter": "2",
                "season": "1",
                "text": "Introduced in Chapter 2, Season 1.",
                "backendValue": 11
              },
              "images": {
                "smallIcon": "https://fortnite-api.com/images/cosmetics/br/bid_384_noshhunter/smallicon.png",
                "icon": "https://fortnite-api.com/images/cosmetics/br/bid_384_noshhunter/icon.png",
                "featured": null,
                "other": null
              },
              "variants": null,
              "gameplayTags": [
                "Cosmetics.Source.ItemShop",
                "Cosmetics.Set.GardenBones",
                "Cosmetics.Filter.Season.11"
              ],
              "showcaseVideo": null,
              "displayAssetPath": null,
              "definitionPath": null,
              "path": "FortniteGame/Content/Athena/Items/Cosmetics/Backpacks/BID_384_NoshHunter",
              "added": "2019-11-20T12:51:14Z",
              "shopHistory": [
                "2020-10-04T00:00:00Z",
                "2020-10-05T00:00:00Z"
              ]
            }
          ]
        },
        {
          "regularPrice": 1200,
          "finalPrice": 1200,
          "bundle": null,
          "banner": null,
          "giftable": true,
          "refundable": true,
          "sortPriority": -1,
          "categories": [
            "Panel 1"
          ],
          "devName": "[VIRTUAL]1 x Snuggs, 1 x Broken Heart for 1200 MtxCurrency",
          "offerId": "v2:/445ba8e260be4ed3b2de9c08d338c55882f0d8aebb667d58d0d3c75512dca354",
          "displayAssetPath": "FortniteGame/Content/Catalog/DisplayAssets/DA_Featured_CID_580_Athena_Commando_M_CuddleTeamDark",
          "newDisplayAssetPath": "FortniteGame/Content/Catalog/NewDisplayAssets/DAv2_CID_580_M_CuddleTeamDark",
          "items": [
            {
              "id": "CID_580_Athena_Commando_M_CuddleTeamDark",
              "name": "Snuggs",
              "description": "One broken bear.",
              "type": {
                "value": "outfit",
                "displayValue": "Outfit",
                "backendValue": "AthenaCharacter"
              },
              "rarity": {
                "value": "rare",
                "displayValue": "Rare",
                "backendValue": "EFortRarity::Rare"
              },
              "series": null,
              "set": {
                "value": "Royale Hearts",
                "text": "Part of the Royale Hearts set.",
                "backendValue": "RoyaleHearts"
              },
              "introduction": {
                "chapter": "2",
                "season": "1",
                "text": "Introduced in Chapter 2, Season 1.",
                "backendValue": 11
              },
              "images": {
                "smallIcon": "https://fortnite-api.com/images/cosmetics/br/cid_580_athena_commando_m_cuddleteamdark/smallicon.png",
                "icon": "https://fortnite-api.com/images/cosmetics/br/cid_580_athena_commando_m_cuddleteamdark/icon.png",
                "featured": "https://fortnite-api.com/images/cosmetics/br/cid_580_athena_commando_m_cuddleteamdark/featured.png",
                "other": null
              },
              "variants": null,
              "gameplayTags": [
                "Cosmetics.Source.ItemShop",
                "Cosmetics.Set.RoyaleHearts",
                "Cosmetics.Filter.Season.11"
              ],
              "showcaseVideo": "Up8QQyCXwx0",
              "displayAssetPath": "FortniteGame/Content/Catalog/DisplayAssets/DA_Featured_CID_580_Athena_Commando_M_CuddleTeamDark",
              "definitionPath": "FortniteGame/Content/Athena/Heroes/HID_580_Athena_Commando_M_CuddleTeamDark",
              "path": "FortniteGame/Content/Athena/Items/Cosmetics/Characters/CID_580_Athena_Commando_M_CuddleTeamDark",
              "added": "2019-11-20T12:48:10Z",
              "shopHistory": [
                "2019-10-19T00:00:00Z",
                "2019-10-31T00:00:00Z",
                "2020-10-05T00:00:00Z"
              ]
            },
            {
              "id": "BID_380_CuddleTeamDark",
              "name": "Broken Heart",
              "description": "Stuffed with sadness.",
              "type": {
                "value": "backpack",
                "displayValue": "Back Bling",
                "backendValue": "AthenaBackpack"
              },
              "rarity": {
                "value": "rare",
                "displayValue": "Rare",
                "backendValue": "EFortRarity::Rare"
              },
              "series": null,
              "set": {
                "value": "Royale Hearts",
                "text": "Part of the Royale Hearts set.",
                "backendValue": "RoyaleHearts"
              },
              "introduction": {
                "chapter": "2",
                "season": "1",
                "text": "Introduced in Chapter 2, Season 1.",
                "backendValue": 11
              },
              "images": {
                "smallIcon": "https://fortnite-api.com/images/cosmetics/br/bid_380_cuddleteamdark/smallicon.png",
                "icon": "https://fortnite-api.com/images/cosmetics/br/bid_380_cuddleteamdark/icon.png",
                "featured": null,
                "other": null
              },
              "variants": null,
              "gameplayTags": [
                "Cosmetics.Source.ItemShop",
                "Cosmetics.Set.RoyaleHearts",
                "Cosmetics.Filter.Season.11"
              ],
              "showcaseVideo": null,
              "displayAssetPath": null,
              "definitionPath": null,
              "path": "FortniteGame/Content/Athena/Items/Cosmetics/Backpacks/BID_380_CuddleTeamDark",
              "added": "2019-11-20T12:50:31Z",
              "shopHistory": [
                "2020-10-05T00:00:00Z"
              ]
            }
          ]
        },
        {
          "regularPrice": 800,
          "finalPrice": 800,
          "bundle": null,
          "banner": {
            "value": "Collect the Set!",
            "backendValue": "CollectTheSet"
          },
          "giftable": true,
          "refundable": true,
          "sortPriority": -4,
          "categories": [
            "Panel 2"
          ],
          "devName": "[VIRTUAL]1 x Globber for 800 MtxCurrency",
          "offerId": "v2:/81f767865db128ef01c5a5c1ce3f9bd5b54c368ba35953f36b686f58ffa6fbd2",
          "displayAssetPath": "FortniteGame/Content/Catalog/DisplayAssets/DA_Featured_Pickaxe_ID_303_Nosh",
          "newDisplayAssetPath": "FortniteGame/Content/Catalog/NewDisplayAssets/DAv2_Pickaxe_ID_303_Nosh",
          "items": [
            {
              "id": "Pickaxe_ID_303_Nosh",
              "name": "Globber",
              "description": "Set your globber to clobber.",
              "type": {
                "value": "pickaxe",
                "displayValue": "Harvesting Tool",
                "backendValue": "AthenaPickaxe"
              },
              "rarity": {
                "value": "rare",
                "displayValue": "Rare",
                "backendValue": "EFortRarity::Rare"
              },
              "series": null,
              "set": {
                "value": "Final Reckoning",
                "text": "Part of the Final Reckoning set.",
                "backendValue": "GardenBones"
              },
              "introduction": {
                "chapter": "2",
                "season": "1",
                "text": "Introduced in Chapter 2, Season 1.",
                "backendValue": 11
              },
              "images": {
                "smallIcon": "https://fortnite-api.com/images/cosmetics/br/pickaxe_id_303_nosh/smallicon.png",
                "icon": "https://fortnite-api.com/images/cosmetics/br/pickaxe_id_303_nosh/icon.png",
                "featured": "https://fortnite-api.com/images/cosmetics/br/pickaxe_id_303_nosh/featured.png",
                "other": null
              },
              "variants": null,
              "gameplayTags": [
                "Cosmetics.Set.GardenBones",
                "Cosmetics.Source.ItemShop",
                "Cosmetics.Filter.Season.11"
              ],
              "showcaseVideo": "hofItqmqUds",
              "displayAssetPath": "FortniteGame/Content/Catalog/DisplayAssets/DA_Featured_Pickaxe_ID_303_Nosh",
              "definitionPath": "FortniteGame/Content/Athena/Items/Weapons/WID_Harvest_Pickaxe_Nosh",
              "path": "FortniteGame/Content/Athena/Items/Cosmetics/Pickaxes/Pickaxe_ID_303_Nosh",
              "added": "2019-11-20T12:51:25Z",
              "shopHistory": [
                "2019-10-24T00:00:00Z",
                "2019-11-01T00:00:00Z",
                "2020-10-04T00:00:00Z",
                "2020-10-05T00:00:00Z"
              ]
            }
          ]
        },
        {
          "regularPrice": 800,
          "finalPrice": 800,
          "bundle": null,
          "banner": {
            "value": "Collect the Set!",
            "backendValue": "CollectTheSet"
          },
          "giftable": true,
          "refundable": true,
          "sortPriority": -10,
          "categories": [
            "Panel 4"
          ],
          "devName": "[VIRTUAL]1 x Gnashers for 800 MtxCurrency",
          "offerId": "v2:/58b810e8163d6c9e5a8f83be09733638d76d299712b2db4d58e8fe4bd3939f23",
          "displayAssetPath": "FortniteGame/Content/Catalog/DisplayAssets/DA_Featured_Pickaxe_ID_298_Freak1H",
          "newDisplayAssetPath": "FortniteGame/Content/Catalog/NewDisplayAssets/DAv2_Pickaxe_ID_298_Freak1H",
          "items": [
            {
              "id": "Pickaxe_ID_298_Freak1H",
              "name": "Gnashers",
              "description": "Careful. They bite.",
              "type": {
                "value": "pickaxe",
                "displayValue": "Harvesting Tool",
                "backendValue": "AthenaPickaxe"
              },
              "rarity": {
                "value": "rare",
                "displayValue": "Rare",
                "backendValue": "EFortRarity::Rare"
              },
              "series": null,
              "set": {
                "value": "Fearsome Freaks",
                "text": "Part of the Fearsome Freaks set.",
                "backendValue": "FrighteningOddity"
              },
              "introduction": {
                "chapter": "2",
                "season": "1",
                "text": "Introduced in Chapter 2, Season 1.",
                "backendValue": 11
              },
              "images": {
                "smallIcon": "https://fortnite-api.com/images/cosmetics/br/pickaxe_id_298_freak1h/smallicon.png",
                "icon": "https://fortnite-api.com/images/cosmetics/br/pickaxe_id_298_freak1h/icon.png",
                "featured": "https://fortnite-api.com/images/cosmetics/br/pickaxe_id_298_freak1h/featured.png",
                "other": null
              },
              "variants": null,
              "gameplayTags": [
                "Cosmetics.Pickaxe.DualWield",
                "Cosmetics.Set.FrighteningOddity",
                "Cosmetics.Source.ItemShop",
                "Cosmetics.Filter.Season.11"
              ],
              "showcaseVideo": "T2zNgDgoHnA",
              "displayAssetPath": "FortniteGame/Content/Catalog/DisplayAssets/DA_Featured_Pickaxe_ID_298_Freak1H",
              "definitionPath": "FortniteGame/Content/Athena/Items/Weapons/WID_Harvest_Pickaxe_Freak1H",
              "path": "FortniteGame/Content/Athena/Items/Cosmetics/Pickaxes/Pickaxe_ID_298_Freak1H",
              "added": "2019-11-20T12:51:25Z",
              "shopHistory": [
                "2019-10-28T00:00:00Z",
                "2019-11-04T00:00:00Z",
                "2020-10-03T00:00:00Z",
                "2020-10-04T00:00:00Z",
                "2020-10-05T00:00:00Z"
              ]
            }
          ]
        },
        {
          "regularPrice": 800,
          "finalPrice": 800,
          "bundle": null,
          "banner": {
            "value": "Collect the Set!",
            "backendValue": "CollectTheSet"
          },
          "giftable": true,
          "refundable": true,
          "sortPriority": -5,
          "categories": [
            "Panel 2"
          ],
          "devName": "[VIRTUAL]1 x Goo Glider for 800 MtxCurrency",
          "offerId": "v2:/41b5207c6dca3ab70d303ec5cf78af179d5ee8d1d2075b8c1a0d642c0c72ed41",
          "displayAssetPath": "FortniteGame/Content/Catalog/DisplayAssets/DA_Featured_Glider_ID_185_Nosh",
          "newDisplayAssetPath": "FortniteGame/Content/Catalog/NewDisplayAssets/DAv2_Glider_ID_185_Nosh",
          "items": [
            {
              "id": "Glider_ID_185_Nosh",
              "name": "Goo Glider",
              "description": "Soar with gummy goodness.",
              "type": {
                "value": "glider",
                "displayValue": "Glider",
                "backendValue": "AthenaGlider"
              },
              "rarity": {
                "value": "rare",
                "displayValue": "Rare",
                "backendValue": "EFortRarity::Rare"
              },
              "series": null,
              "set": {
                "value": "Final Reckoning",
                "text": "Part of the Final Reckoning set.",
                "backendValue": "GardenBones"
              },
              "introduction": {
                "chapter": "2",
                "season": "1",
                "text": "Introduced in Chapter 2, Season 1.",
                "backendValue": 11
              },
              "images": {
                "smallIcon": "https://fortnite-api.com/images/cosmetics/br/glider_id_185_nosh/smallicon.png",
                "icon": "https://fortnite-api.com/images/cosmetics/br/glider_id_185_nosh/icon.png",
                "featured": "https://fortnite-api.com/images/cosmetics/br/glider_id_185_nosh/featured.png",
                "other": null
              },
              "variants": null,
              "gameplayTags": [
                "Cosmetics.Set.GardenBones",
                "Cosmetics.Source.ItemShop",
                "Cosmetics.Filter.Season.11"
              ],
              "showcaseVideo": "RECsVUoI46I",
              "displayAssetPath": "FortniteGame/Content/Catalog/DisplayAssets/DA_Featured_Glider_ID_185_Nosh",
              "definitionPath": null,
              "path": "FortniteGame/Content/Athena/Items/Cosmetics/Gliders/Glider_ID_185_Nosh",
              "added": "2019-11-20T12:51:19Z",
              "shopHistory": [
                "2019-10-24T00:00:00Z",
                "2019-11-01T00:00:00Z",
                "2020-10-04T00:00:00Z",
                "2020-10-05T00:00:00Z"
              ]
            }
          ]
        },
        {
          "regularPrice": 800,
          "finalPrice": 800,
          "bundle": null,
          "banner": {
            "value": "Collect the Set!",
            "backendValue": "CollectTheSet"
          },
          "giftable": true,
          "refundable": true,
          "sortPriority": -8,
          "categories": [
            "Panel 3"
          ],
          "devName": "[VIRTUAL]1 x Spellbound Staff for 800 MtxCurrency",
          "offerId": "v2:/94fd9aea38f3e10a2f512bdcb32973c3ecb36ad4b54957f00cf24f2078bda1da",
          "displayAssetPath": "FortniteGame/Content/Catalog/DisplayAssets/DA_Featured_Pickaxe_ID_299_GoatRobe",
          "newDisplayAssetPath": "FortniteGame/Content/Catalog/NewDisplayAssets/DAv2_Pickaxe_ID_299_Goatrobe",
          "items": [
            {
              "id": "Pickaxe_ID_299_GoatRobe",
              "name": "Spellbound Staff",
              "description": "Bend reality to your will.",
              "type": {
                "value": "pickaxe",
                "displayValue": "Harvesting Tool",
                "backendValue": "AthenaPickaxe"
              },
              "rarity": {
                "value": "rare",
                "displayValue": "Rare",
                "backendValue": "EFortRarity::Rare"
              },
              "series": null,
              "set": {
                "value": "Arcane Arts",
                "text": "Part of the Arcane Arts set.",
                "backendValue": "Witch"
              },
              "introduction": {
                "chapter": "2",
                "season": "1",
                "text": "Introduced in Chapter 2, Season 1.",
                "backendValue": 11
              },
              "images": {
                "smallIcon": "https://fortnite-api.com/images/cosmetics/br/pickaxe_id_299_goatrobe/smallicon.png",
                "icon": "https://fortnite-api.com/images/cosmetics/br/pickaxe_id_299_goatrobe/icon.png",
                "featured": "https://fortnite-api.com/images/cosmetics/br/pickaxe_id_299_goatrobe/featured.png",
                "other": null
              },
              "variants": null,
              "gameplayTags": [
                "Cosmetics.Set.Witch",
                "Cosmetics.Source.ItemShop",
                "Cosmetics.Filter.Season.11"
              ],
              "showcaseVideo": "3ki3aj3-uSI",
              "displayAssetPath": "FortniteGame/Content/Catalog/DisplayAssets/DA_Featured_Pickaxe_ID_299_GoatRobe",
              "definitionPath": "FortniteGame/Content/Athena/Items/Weapons/WID_Harvest_Pickaxe_GoatRobe",
              "path": "FortniteGame/Content/Athena/Items/Cosmetics/Pickaxes/Pickaxe_ID_299_GoatRobe",
              "added": "2019-11-20T12:51:25Z",
              "shopHistory": [
                "2019-10-26T00:00:00Z",
                "2019-10-27T00:00:00Z",
                "2019-11-03T00:00:00Z",
                "2019-11-04T00:00:00Z",
                "2020-10-03T00:00:00Z",
                "2020-10-04T00:00:00Z",
                "2020-10-05T00:00:00Z"
              ]
            }
          ]
        },
        {
          "regularPrice": 800,
          "finalPrice": 800,
          "bundle": null,
          "banner": {
            "value": "Collect the Set!",
            "backendValue": "CollectTheSet"
          },
          "giftable": true,
          "refundable": true,
          "sortPriority": -2,
          "categories": [
            "Panel 1"
          ],
          "devName": "[VIRTUAL]1 x Stickers for 800 MtxCurrency",
          "offerId": "v2:/8f8b619a88f9a895f78549154e7d011d99ddcb3c33da16bfacb9643e49cb9a1e",
          "displayAssetPath": "FortniteGame/Content/Catalog/DisplayAssets/DA_Featured_Pickaxe_ID_304_NoshHunter1H",
          "newDisplayAssetPath": "FortniteGame/Content/Catalog/NewDisplayAssets/DAv2_Pickaxe_ID_304_NoshHunter1h",
          "items": [
            {
              "id": "Pickaxe_ID_304_NoshHunter1H",
              "name": "Stickers",
              "description": "Sharp and sticky.",
              "type": {
                "value": "pickaxe",
                "displayValue": "Harvesting Tool",
                "backendValue": "AthenaPickaxe"
              },
              "rarity": {
                "value": "rare",
                "displayValue": "Rare",
                "backendValue": "EFortRarity::Rare"
              },
              "series": null,
              "set": {
                "value": "Final Reckoning",
                "text": "Part of the Final Reckoning set.",
                "backendValue": "GardenBones"
              },
              "introduction": {
                "chapter": "2",
                "season": "1",
                "text": "Introduced in Chapter 2, Season 1.",
                "backendValue": 11
              },
              "images": {
                "smallIcon": "https://fortnite-api.com/images/cosmetics/br/pickaxe_id_304_noshhunter1h/smallicon.png",
                "icon": "https://fortnite-api.com/images/cosmetics/br/pickaxe_id_304_noshhunter1h/icon.png",
                "featured": "https://fortnite-api.com/images/cosmetics/br/pickaxe_id_304_noshhunter1h/featured.png",
                "other": null
              },
              "variants": null,
              "gameplayTags": [
                "Cosmetics.Pickaxe.DualWield",
                "Cosmetics.Set.GardenBones",
                "Cosmetics.Source.ItemShop",
                "Cosmetics.Filter.Season.11"
              ],
              "showcaseVideo": "qE-k86vokvY",
              "displayAssetPath": "FortniteGame/Content/Catalog/DisplayAssets/DA_Featured_Pickaxe_ID_304_NoshHunter1H",
              "definitionPath": "FortniteGame/Content/Athena/Items/Weapons/WID_Harvest_Pickaxe_NoshHunter1H",
              "path": "FortniteGame/Content/Athena/Items/Cosmetics/Pickaxes/Pickaxe_ID_304_NoshHunter1H",
              "added": "2019-11-20T12:51:25Z",
              "shopHistory": [
                "2019-10-24T00:00:00Z",
                "2019-11-01T00:00:00Z",
                "2020-10-04T00:00:00Z",
                "2020-10-05T00:00:00Z"
              ]
            }
          ]
        },
        {
          "regularPrice": 500,
          "finalPrice": 500,
          "bundle": null,
          "banner": null,
          "giftable": true,
          "refundable": true,
          "sortPriority": -6,
          "categories": [
            "Panel 3"
          ],
          "devName": "[VIRTUAL]1 x Say So for 500 MtxCurrency",
          "offerId": "v2:/d7c742742dff742ce7fad7644d8a58b60ec1ced8278b820f2f76332065b2d862",
          "displayAssetPath": null,
          "newDisplayAssetPath": "FortniteGame/Content/Catalog/NewDisplayAssets/DAv2_EID_HotPink",
          "items": [
            {
              "id": "EID_HotPink",
              "name": "Say So",
              "description": "Roll with the changes.",
              "type": {
                "value": "emote",
                "displayValue": "Emote",
                "backendValue": "AthenaDance"
              },
              "rarity": {
                "value": "rare",
                "displayValue": "Rare",
                "backendValue": "EFortRarity::Rare"
              },
              "series": null,
              "set": null,
              "introduction": {
                "chapter": "2",
                "season": "4",
                "text": "Introduced in Chapter 2, Season 4.",
                "backendValue": 14
              },
              "images": {
                "smallIcon": "https://fortnite-api.com/images/cosmetics/br/eid_hotpink/smallicon.png",
                "icon": "https://fortnite-api.com/images/cosmetics/br/eid_hotpink/icon.png",
                "featured": null,
                "other": null
              },
              "variants": null,
              "gameplayTags": [
                "Cosmetics.EmoteType.Dance",
                "Cosmetics.Source.ItemShop",
                "Cosmetics.Filter.Season.14"
              ],
              "showcaseVideo": "ekUxGBc-z5A",
              "displayAssetPath": null,
              "definitionPath": null,
              "path": "FortniteGame/Content/Athena/Items/Cosmetics/Dances/EID_HotPink",
              "added": "2020-08-27T06:07:50Z",
              "shopHistory": [
                "2020-09-05T00:00:00Z",
                "2020-09-06T00:00:00Z",
                "2020-10-05T00:00:00Z"
              ]
            }
          ]
        },
        {
          "regularPrice": 500,
          "finalPrice": 500,
          "bundle": null,
          "banner": {
            "value": "Animated!",
            "backendValue": "Animated"
          },
          "giftable": true,
          "refundable": true,
          "sortPriority": -3,
          "categories": [
            "Panel 1"
          ],
          "devName": "[VIRTUAL]1 x Snuggs Shine for 500 MtxCurrency",
          "offerId": "v2:/c9e7de7c052a4add301c764aa887413cd3d055f1546443aa07add5bde09d8fbf",
          "displayAssetPath": "FortniteGame/Content/Catalog/DisplayAssets/DA_Featured_Wrap_157_CuddleTeamDark",
          "newDisplayAssetPath": "FortniteGame/Content/Catalog/NewDisplayAssets/DAv2_Wrap_157_CuddleTeamDark",
          "items": [
            {
              "id": "Wrap_157_CuddleTeamDark",
              "name": "Snuggs Shine",
              "description": "Show your style.",
              "type": {
                "value": "wrap",
                "displayValue": "Wrap",
                "backendValue": "AthenaItemWrap"
              },
              "rarity": {
                "value": "rare",
                "displayValue": "Rare",
                "backendValue": "EFortRarity::Rare"
              },
              "series": null,
              "set": {
                "value": "Royale Hearts",
                "text": "Part of the Royale Hearts set.",
                "backendValue": "RoyaleHearts"
              },
              "introduction": {
                "chapter": "2",
                "season": "1",
                "text": "Introduced in Chapter 2, Season 1.",
                "backendValue": 11
              },
              "images": {
                "smallIcon": "https://fortnite-api.com/images/cosmetics/br/wrap_157_cuddleteamdark/smallicon.png",
                "icon": "https://fortnite-api.com/images/cosmetics/br/wrap_157_cuddleteamdark/icon.png",
                "featured": "https://fortnite-api.com/images/cosmetics/br/wrap_157_cuddleteamdark/featured.png",
                "other": null
              },
              "variants": null,
              "gameplayTags": [
                "Cosmetics.Source.ItemShop",
                "Cosmetics.UserFacingFlags.Wrap.Animated",
                "Cosmetics.Set.RoyaleHearts",
                "Cosmetics.Filter.Season.11"
              ],
              "showcaseVideo": "ygLOhG6_bV4",
              "displayAssetPath": "FortniteGame/Content/Catalog/DisplayAssets/DA_Featured_Wrap_157_CuddleTeamDark",
              "definitionPath": null,
              "path": "FortniteGame/Content/Athena/Items/Cosmetics/ItemWraps/Wrap_157_CuddleTeamDark",
              "added": "2019-11-20T12:48:19Z",
              "shopHistory": [
                "2019-10-19T00:00:00Z",
                "2019-10-31T00:00:00Z",
                "2020-10-05T00:00:00Z"
              ]
            }
          ]
        },
        {
          "regularPrice": 500,
          "finalPrice": 500,
          "bundle": null,
          "banner": {
            "value": "Animated!",
            "backendValue": "Animated"
          },
          "giftable": true,
          "refundable": true,
          "sortPriority": -11,
          "categories": [
            "Panel 4"
          ],
          "devName": "[VIRTUAL]1 x Toothsome for 500 MtxCurrency",
          "offerId": "v2:/953766322194e12b203a073651b03716701dfc657e2bd23331f2789915fe0ab6",
          "displayAssetPath": "FortniteGame/Content/Catalog/DisplayAssets/DA_Featured_Wrap_159_Freak",
          "newDisplayAssetPath": "FortniteGame/Content/Catalog/NewDisplayAssets/DAv2_Wrap_159_Freak",
          "items": [
            {
              "id": "Wrap_159_Freak",
              "name": "Toothsome",
              "description": "Show your style.",
              "type": {
                "value": "wrap",
                "displayValue": "Wrap",
                "backendValue": "AthenaItemWrap"
              },
              "rarity": {
                "value": "rare",
                "displayValue": "Rare",
                "backendValue": "EFortRarity::Rare"
              },
              "series": null,
              "set": {
                "value": "Fearsome Freaks",
                "text": "Part of the Fearsome Freaks set.",
                "backendValue": "FrighteningOddity"
              },
              "introduction": {
                "chapter": "2",
                "season": "1",
                "text": "Introduced in Chapter 2, Season 1.",
                "backendValue": 11
              },
              "images": {
                "smallIcon": "https://fortnite-api.com/images/cosmetics/br/wrap_159_freak/smallicon.png",
                "icon": "https://fortnite-api.com/images/cosmetics/br/wrap_159_freak/icon.png",
                "featured": "https://fortnite-api.com/images/cosmetics/br/wrap_159_freak/featured.png",
                "other": null
              },
              "variants": null,
              "gameplayTags": [
                "Cosmetics.Set.FrighteningOddity",
                "Cosmetics.Source.ItemShop",
                "Cosmetics.UserFacingFlags.Wrap.Animated",
                "Cosmetics.Filter.Season.11"
              ],
              "showcaseVideo": "N6NZxwuIUsU",
              "displayAssetPath": "FortniteGame/Content/Catalog/DisplayAssets/DA_Featured_Wrap_159_Freak",
              "definitionPath": null,
              "path": "FortniteGame/Content/Athena/Items/Cosmetics/ItemWraps/Wrap_159_Freak",
              "added": "2019-11-20T12:51:21Z",
              "shopHistory": [
                "2019-10-28T00:00:00Z",
                "2019-11-04T00:00:00Z",
                "2020-10-03T00:00:00Z",
                "2020-10-04T00:00:00Z",
                "2020-10-05T00:00:00Z"
              ]
            }
          ]
        },
        {
          "regularPrice": 800,
          "finalPrice": 800,
          "bundle": null,
          "banner": null,
          "giftable": true,
          "refundable": true,
          "sortPriority": -7,
          "categories": [
            "Panel 4"
          ],
          "devName": "[VIRTUAL]1 x Scarlet Commander for 800 MtxCurrency",
          "offerId": "v2:/09256e608ee2b021ac0f4667bdb59f7d34c9ddfd1bd9f83dd96c86fdb7660638",
          "displayAssetPath": "FortniteGame/Content/Catalog/DisplayAssets/DA_Featured_CID_734_Athena_Commando_F_BannerRed",
          "newDisplayAssetPath": "FortniteGame/Content/Catalog/NewDisplayAssets/DAv2_CID_734_F_BannerRed",
          "items": [
            {
              "id": "CID_734_Athena_Commando_F_BannerRed",
              "name": "Scarlet Commander",
              "description": "Unknown and unforgettable.",
              "type": {
                "value": "outfit",
                "displayValue": "Outfit",
                "backendValue": "AthenaCharacter"
              },
              "rarity": {
                "value": "uncommon",
                "displayValue": "Uncommon",
                "backendValue": "EFortRarity::Uncommon"
              },
              "series": null,
              "set": {
                "value": "Nightfire",
                "text": "Part of the Nightfire set.",
                "backendValue": "LateShot"
              },
              "introduction": {
                "chapter": "2",
                "season": "2",
                "text": "Introduced in Chapter 2, Season 2.",
                "backendValue": 12
              },
              "images": {
                "smallIcon": "https://fortnite-api.com/images/cosmetics/br/cid_734_athena_commando_f_bannerred/smallicon.png",
                "icon": "https://fortnite-api.com/images/cosmetics/br/cid_734_athena_commando_f_bannerred/icon.png",
                "featured": "https://fortnite-api.com/images/cosmetics/br/cid_734_athena_commando_f_bannerred/featured.png",
                "other": null
              },
              "variants": null,
              "gameplayTags": [
                "Cosmetics.Source.ItemShop",
                "Cosmetics.Filter.Season.12",
                "Cosmetics.Set.LateShot"
              ],
              "showcaseVideo": "VOMv1eEXdoM",
              "displayAssetPath": "FortniteGame/Content/Catalog/DisplayAssets/DA_Featured_CID_734_Athena_Commando_F_BannerRed",
              "definitionPath": "FortniteGame/Content/Athena/Heroes/HID_734_Athena_Commando_F_BannerRed",
              "path": "FortniteGame/Content/Athena/Items/Cosmetics/Characters/CID_734_Athena_Commando_F_BannerRed",
              "added": "2020-03-17T11:00:47Z",
              "shopHistory": [
                "2020-03-22T00:00:00Z",
                "2020-03-23T00:00:00Z",
                "2020-04-26T00:00:00Z",
                "2020-05-25T00:00:00Z",
                "2020-06-26T00:00:00Z",
                "2020-07-28T00:00:00Z",
                "2020-09-01T00:00:00Z",
                "2020-10-05T00:00:00Z"
              ]
            }
          ]
        },
        {
          "regularPrice": 500,
          "finalPrice": 500,
          "bundle": null,
          "banner": {
            "value": "Collect the Set!",
            "backendValue": "CollectTheSet"
          },
          "giftable": true,
          "refundable": true,
          "sortPriority": -2,
          "categories": [
            "Panel 1"
          ],
          "devName": "[VIRTUAL]1 x Snuggle Swiper for 500 MtxCurrency",
          "offerId": "v2:/28f0b464f70b0b048ed6b0a5a6038a43a57a5ab81cefad3cd7c07b2bda74fef6",
          "displayAssetPath": "FortniteGame/Content/Catalog/DisplayAssets/DA_Featured_Pickaxe_ID_285_CuddleTeamDark",
          "newDisplayAssetPath": "FortniteGame/Content/Catalog/NewDisplayAssets/DAv2_Pickaxe_ID_285_CuddleTeamDark",
          "items": [
            {
              "id": "Pickaxe_ID_285_CuddleTeamDark",
              "name": "Snuggle Swiper",
              "description": "Love 'em to pieces.",
              "type": {
                "value": "pickaxe",
                "displayValue": "Harvesting Tool",
                "backendValue": "AthenaPickaxe"
              },
              "rarity": {
                "value": "uncommon",
                "displayValue": "Uncommon",
                "backendValue": "EFortRarity::Uncommon"
              },
              "series": null,
              "set": {
                "value": "Royale Hearts",
                "text": "Part of the Royale Hearts set.",
                "backendValue": "RoyaleHearts"
              },
              "introduction": {
                "chapter": "2",
                "season": "1",
                "text": "Introduced in Chapter 2, Season 1.",
                "backendValue": 11
              },
              "images": {
                "smallIcon": "https://fortnite-api.com/images/cosmetics/br/pickaxe_id_285_cuddleteamdark/smallicon.png",
                "icon": "https://fortnite-api.com/images/cosmetics/br/pickaxe_id_285_cuddleteamdark/icon.png",
                "featured": "https://fortnite-api.com/images/cosmetics/br/pickaxe_id_285_cuddleteamdark/featured.png",
                "other": null
              },
              "variants": null,
              "gameplayTags": [
                "Cosmetics.Set.RoyaleHearts",
                "Cosmetics.Source.ItemShop",
                "Cosmetics.Filter.Season.11"
              ],
              "showcaseVideo": "1mUevnGXNxM",
              "displayAssetPath": "FortniteGame/Content/Catalog/DisplayAssets/DA_Featured_Pickaxe_ID_285_CuddleTeamDark",
              "definitionPath": "FortniteGame/Content/Athena/Items/Weapons/WID_Harvest_Pickaxe_CuddleTeamDark",
              "path": "FortniteGame/Content/Athena/Items/Cosmetics/Pickaxes/Pickaxe_ID_285_CuddleTeamDark",
              "added": "2019-11-20T12:50:42Z",
              "shopHistory": [
                "2019-10-19T00:00:00Z",
                "2019-10-31T00:00:00Z",
                "2020-10-05T00:00:00Z"
              ]
            }
          ]
        },
        {
          "regularPrice": 300,
          "finalPrice": 300,
          "bundle": null,
          "banner": {
            "value": "Collect the Set!",
            "backendValue": "CollectTheSet"
          },
          "giftable": true,
          "refundable": true,
          "sortPriority": -6,
          "categories": [
            "Panel 2"
          ],
          "devName": "[VIRTUAL]1 x Noshy for 300 MtxCurrency",
          "offerId": "v2:/6791e0bc3d2832ec97203f90ca6e88879ab6f08ac0c2bd272195b32e0c94cb92",
          "displayAssetPath": "FortniteGame/Content/Catalog/DisplayAssets/DA_Featured_Wrap_161_Nosh",
          "newDisplayAssetPath": "FortniteGame/Content/Catalog/NewDisplayAssets/DAv2_Wrap_161_Nosh",
          "items": [
            {
              "id": "Wrap_161_Nosh",
              "name": "Noshy",
              "description": "Show your style.",
              "type": {
                "value": "wrap",
                "displayValue": "Wrap",
                "backendValue": "AthenaItemWrap"
              },
              "rarity": {
                "value": "uncommon",
                "displayValue": "Uncommon",
                "backendValue": "EFortRarity::Uncommon"
              },
              "series": null,
              "set": {
                "value": "Final Reckoning",
                "text": "Part of the Final Reckoning set.",
                "backendValue": "GardenBones"
              },
              "introduction": {
                "chapter": "2",
                "season": "1",
                "text": "Introduced in Chapter 2, Season 1.",
                "backendValue": 11
              },
              "images": {
                "smallIcon": "https://fortnite-api.com/images/cosmetics/br/wrap_161_nosh/smallicon.png",
                "icon": "https://fortnite-api.com/images/cosmetics/br/wrap_161_nosh/icon.png",
                "featured": "https://fortnite-api.com/images/cosmetics/br/wrap_161_nosh/featured.png",
                "other": null
              },
              "variants": null,
              "gameplayTags": [
                "Cosmetics.Set.GardenBones",
                "Cosmetics.Source.ItemShop",
                "Cosmetics.Filter.Season.11"
              ],
              "showcaseVideo": "hnuHKn0tO1Q",
              "displayAssetPath": "FortniteGame/Content/Catalog/DisplayAssets/DA_Featured_Wrap_161_Nosh",
              "definitionPath": null,
              "path": "FortniteGame/Content/Athena/Items/Cosmetics/ItemWraps/Wrap_161_Nosh",
              "added": "2019-11-20T12:51:21Z",
              "shopHistory": [
                "2019-10-24T00:00:00Z",
                "2020-10-04T00:00:00Z",
                "2020-10-05T00:00:00Z"
              ]
            }
          ]
        }
      ]
    },
    "daily": {
      "name": "Daily",
      "entries": [
        {
          "regularPrice": 1200,
          "finalPrice": 1200,
          "bundle": null,
          "banner": {
            "value": "Selectable Styles!",
            "backendValue": "SelectableStyles"
          },
          "giftable": true,
          "refundable": true,
          "sortPriority": -1,
          "categories": [
            "Daily 1"
          ],
          "devName": "[VIRTUAL]1 x Bachii, 1 x Mochi for 1200 MtxCurrency",
          "offerId": "v2:/8dc3c61b5c5b40798d5fbf63668b484d20ec9cfd8b0811e49503367c60b00284",
          "displayAssetPath": "FortniteGame/Content/Catalog/DisplayAssets/DA_Featured_CID_471_Athena_Commando_F_Bani",
          "newDisplayAssetPath": "FortniteGame/Content/Catalog/NewDisplayAssets/DAv2_CID_471_f_bani",
          "items": [
            {
              "id": "CID_471_Athena_Commando_F_Bani",
              "name": "Bachii",
              "description": "Adorably mysterious.",
              "type": {
                "value": "outfit",
                "displayValue": "Outfit",
                "backendValue": "AthenaCharacter"
              },
              "rarity": {
                "value": "rare",
                "displayValue": "Rare",
                "backendValue": "EFortRarity::Rare"
              },
              "series": null,
              "set": {
                "value": "Battle Bun",
                "text": "Part of the Battle Bun set.",
                "backendValue": "Bani"
              },
              "introduction": {
                "chapter": "1",
                "season": "9",
                "text": "Introduced in Chapter 1, Season 9.",
                "backendValue": 9
              },
              "images": {
                "smallIcon": "https://fortnite-api.com/images/cosmetics/br/cid_471_athena_commando_f_bani/smallicon.png",
                "icon": "https://fortnite-api.com/images/cosmetics/br/cid_471_athena_commando_f_bani/icon.png",
                "featured": "https://fortnite-api.com/images/cosmetics/br/cid_471_athena_commando_f_bani/featured.png",
                "other": null
              },
              "variants": [
                {
                  "channel": "Material",
                  "type": "STYLE",
                  "options": [
                    {
                      "tag": "Mat1",
                      "name": "DEFAULT",
                      "unlockRequirements": null,
                      "image": "https://fortnite-api.com/images/cosmetics/br/cid_471_athena_commando_f_bani/variants/material/mat1.png"
                    },
                    {
                      "tag": "Mat2",
                      "name": "SPY",
                      "unlockRequirements": null,
                      "image": "https://fortnite-api.com/images/cosmetics/br/cid_471_athena_commando_f_bani/variants/material/mat2.png"
                    }
                  ]
                }
              ],
              "gameplayTags": [
                "Cosmetics.Source.ItemShop",
                "Cosmetics.Set.Bani",
                "Cosmetics.Filter.Season.9",
                "Cosmetics.UserFacingFlags.HasVariants"
              ],
              "showcaseVideo": "fXmcGFWDn4g",
              "displayAssetPath": "FortniteGame/Content/Catalog/DisplayAssets/DA_Featured_CID_471_Athena_Commando_F_Bani",
              "definitionPath": "FortniteGame/Content/Athena/Heroes/HID_471_Athena_Commando_F_Bani",
              "path": "FortniteGame/Content/Athena/Items/Cosmetics/Characters/CID_471_Athena_Commando_F_Bani",
              "added": "2019-11-20T12:49:55Z",
              "shopHistory": [
                "2019-07-30T00:00:00Z",
                "2019-07-31T00:00:00Z",
                "2020-06-02T00:00:00Z",
                "2020-07-07T00:00:00Z",
                "2020-08-12T00:00:00Z",
                "2020-09-13T00:00:00Z",
                "2020-10-05T00:00:00Z"
              ]
            },
            {
              "id": "BID_307_Bani",
              "name": "Mochi",
              "description": "So sweet.",
              "type": {
                "value": "backpack",
                "displayValue": "Back Bling",
                "backendValue": "AthenaBackpack"
              },
              "rarity": {
                "value": "rare",
                "displayValue": "Rare",
                "backendValue": "EFortRarity::Rare"
              },
              "series": null,
              "set": {
                "value": "Battle Bun",
                "text": "Part of the Battle Bun set.",
                "backendValue": "Bani"
              },
              "introduction": {
                "chapter": "1",
                "season": "9",
                "text": "Introduced in Chapter 1, Season 9.",
                "backendValue": 9
              },
              "images": {
                "smallIcon": "https://fortnite-api.com/images/cosmetics/br/bid_307_bani/smallicon.png",
                "icon": "https://fortnite-api.com/images/cosmetics/br/bid_307_bani/icon.png",
                "featured": null,
                "other": null
              },
              "variants": null,
              "gameplayTags": [
                "Cosmetics.Set.Bani",
                "Cosmetics.Source.ItemShop",
                "Cosmetics.Filter.Season.9"
              ],
              "showcaseVideo": null,
              "displayAssetPath": null,
              "definitionPath": null,
              "path": "FortniteGame/Content/Athena/Items/Cosmetics/Backpacks/BID_307_Bani",
              "added": "2019-11-20T12:50:33Z",
              "shopHistory": [
                "2020-06-02T00:00:00Z",
                "2020-07-07T00:00:00Z",
                "2020-08-12T00:00:00Z",
                "2020-09-13T00:00:00Z",
                "2020-10-05T00:00:00Z"
              ]
            }
          ]
        },
        {
          "regularPrice": 500,
          "finalPrice": 500,
          "bundle": null,
          "banner": null,
          "giftable": true,
          "refundable": true,
          "sortPriority": -5,
          "categories": [
            "Daily 5"
          ],
          "devName": "[VIRTUAL]1 x Criss Cross for 500 MtxCurrency",
          "offerId": "v2:/4cbee9c6eca478c4695a1560e3aafa6985016291f36922664a2f75f3bec31d53",
          "displayAssetPath": null,
          "newDisplayAssetPath": "FortniteGame/Content/Catalog/NewDisplayAssets/DAv2_EID_CrissCross",
          "items": [
            {
              "id": "EID_CrissCross",
              "name": "Criss Cross",
              "description": "Get your point across.",
              "type": {
                "value": "emote",
                "displayValue": "Emote",
                "backendValue": "AthenaDance"
              },
              "rarity": {
                "value": "rare",
                "displayValue": "Rare",
                "backendValue": "EFortRarity::Rare"
              },
              "series": null,
              "set": null,
              "introduction": {
                "chapter": "1",
                "season": "6",
                "text": "Introduced in Chapter 1, Season 6.",
                "backendValue": 6
              },
              "images": {
                "smallIcon": "https://fortnite-api.com/images/cosmetics/br/eid_crisscross/smallicon.png",
                "icon": "https://fortnite-api.com/images/cosmetics/br/eid_crisscross/icon.png",
                "featured": null,
                "other": null
              },
              "variants": null,
              "gameplayTags": [
                "Cosmetics.EmoteType.Dance",
                "Cosmetics.Source.ItemShop",
                "Cosmetics.Filter.Season.6"
              ],
              "showcaseVideo": "oSryzOTMZKk",
              "displayAssetPath": null,
              "definitionPath": null,
              "path": "FortniteGame/Content/Athena/Items/Cosmetics/Dances/EID_CrissCross",
              "added": "2019-11-20T12:48:10Z",
              "shopHistory": [
                "2018-11-03T00:00:00Z",
                "2018-12-03T00:00:00Z",
                "2019-01-09T00:00:00Z",
                "2019-03-09T00:00:00Z",
                "2019-04-11T00:00:00Z",
                "2019-08-06T00:00:00Z",
                "2019-11-07T00:00:00Z",
                "2019-12-08T00:00:00Z",
                "2020-01-15T00:00:00Z",
                "2020-04-07T00:00:00Z",
                "2020-06-15T00:00:00Z",
                "2020-07-22T00:00:00Z",
                "2020-08-15T00:00:00Z",
                "2020-09-15T00:00:00Z",
                "2020-10-05T00:00:00Z"
              ]
            }
          ]
        },
        {
          "regularPrice": 500,
          "finalPrice": 500,
          "bundle": null,
          "banner": {
            "value": "Animated!",
            "backendValue": "Animated"
          },
          "giftable": true,
          "refundable": true,
          "sortPriority": -3,
          "categories": [
            "Daily 3"
          ],
          "devName": "[VIRTUAL]1 x Prismatic Edge for 500 MtxCurrency",
          "offerId": "v2:/f1abe493af6bf41223f490d96bc0ec25a94aa7968888a8e76337f0f2abcd692c",
          "displayAssetPath": "FortniteGame/Content/Catalog/DisplayAssets/DA_Featured_Wrap_139_Prismatic",
          "newDisplayAssetPath": "FortniteGame/Content/Catalog/NewDisplayAssets/DAv2_Wrap_139_Prismatic",
          "items": [
            {
              "id": "Wrap_139_Prismatic",
              "name": "Prismatic Edge",
              "description": "Show your style.",
              "type": {
                "value": "wrap",
                "displayValue": "Wrap",
                "backendValue": "AthenaItemWrap"
              },
              "rarity": {
                "value": "rare",
                "displayValue": "Rare",
                "backendValue": "EFortRarity::Rare"
              },
              "series": null,
              "set": null,
              "introduction": {
                "chapter": "1",
                "season": "X",
                "text": "Introduced in Chapter 1, Season X.",
                "backendValue": 10
              },
              "images": {
                "smallIcon": "https://fortnite-api.com/images/cosmetics/br/wrap_139_prismatic/smallicon.png",
                "icon": "https://fortnite-api.com/images/cosmetics/br/wrap_139_prismatic/icon.png",
                "featured": "https://fortnite-api.com/images/cosmetics/br/wrap_139_prismatic/featured.png",
                "other": null
              },
              "variants": null,
              "gameplayTags": [
                "Cosmetics.Source.ItemShop",
                "Cosmetics.UserFacingFlags.Wrap.Animated",
                "Cosmetics.Filter.Season.10"
              ],
              "showcaseVideo": "052Vr3kxkN4",
              "displayAssetPath": "FortniteGame/Content/Catalog/DisplayAssets/DA_Featured_Wrap_139_Prismatic",
              "definitionPath": null,
              "path": "FortniteGame/Content/Athena/Items/Cosmetics/ItemWraps/Wrap_139_Prismatic",
              "added": "2019-11-20T12:48:20Z",
              "shopHistory": [
                "2019-09-24T00:00:00Z",
                "2019-11-20T00:00:00Z",
                "2020-01-01T00:00:00Z",
                "2020-02-10T00:00:00Z",
                "2020-04-01T00:00:00Z",
                "2020-04-23T00:00:00Z",
                "2020-08-09T00:00:00Z",
                "2020-10-05T00:00:00Z"
              ]
            }
          ]
        },
        {
          "regularPrice": 800,
          "finalPrice": 800,
          "bundle": null,
          "banner": null,
          "giftable": true,
          "refundable": true,
          "sortPriority": -2,
          "categories": [
            "Daily 2"
          ],
          "devName": "[VIRTUAL]1 x Recon Ranger for 800 MtxCurrency",
          "offerId": "v2:/6e30f9077ab7628f4c29e7a629360631dd4aaf2f88155c496ac62089db72c235",
          "displayAssetPath": null,
          "newDisplayAssetPath": "FortniteGame/Content/Catalog/NewDisplayAssets/DAv2_CID_503_F_TacticalWoodlandFuture",
          "items": [
            {
              "id": "CID_503_Athena_Commando_F_TacticalWoodlandFuture",
              "name": "Recon Ranger",
              "description": "Expert field intel ranger.",
              "type": {
                "value": "outfit",
                "displayValue": "Outfit",
                "backendValue": "AthenaCharacter"
              },
              "rarity": {
                "value": "uncommon",
                "displayValue": "Uncommon",
                "backendValue": "EFortRarity::Uncommon"
              },
              "series": null,
              "set": {
                "value": "Advanced Forces",
                "text": "Part of the Advanced Forces set.",
                "backendValue": "AdvancedForces"
              },
              "introduction": {
                "chapter": "1",
                "season": "X",
                "text": "Introduced in Chapter 1, Season X.",
                "backendValue": 10
              },
              "images": {
                "smallIcon": "https://fortnite-api.com/images/cosmetics/br/cid_503_athena_commando_f_tacticalwoodlandfuture/smallicon.png",
                "icon": "https://fortnite-api.com/images/cosmetics/br/cid_503_athena_commando_f_tacticalwoodlandfuture/icon.png",
                "featured": "https://fortnite-api.com/images/cosmetics/br/cid_503_athena_commando_f_tacticalwoodlandfuture/featured.png",
                "other": null
              },
              "variants": null,
              "gameplayTags": [
                "Cosmetics.Source.ItemShop",
                "Cosmetics.Set.AdvancedForces",
                "Cosmetics.Filter.Season.10"
              ],
              "showcaseVideo": "w5BZPWGuAsU",
              "displayAssetPath": "FortniteGame/Content/Catalog/DisplayAssets/DA_Featured_CID_503_Athena_Commando_F_TacticalWoodlandFuture",
              "definitionPath": "FortniteGame/Content/Athena/Heroes/HID_503_Athena_Commando_F_TacticalWoodlandFuture",
              "path": "FortniteGame/Content/Athena/Items/Cosmetics/Characters/CID_503_Athena_Commando_F_TacticalWoodlandFuture",
              "added": "2019-11-20T12:49:52Z",
              "shopHistory": [
                "2019-08-17T00:00:00Z",
                "2019-09-14T00:00:00Z",
                "2019-10-13T00:00:00Z",
                "2019-11-20T00:00:00Z",
                "2019-12-20T00:00:00Z",
                "2020-01-07T00:00:00Z",
                "2020-02-05T00:00:00Z",
                "2020-02-21T00:00:00Z",
                "2020-03-20T00:00:00Z",
                "2020-04-18T00:00:00Z",
                "2020-04-25T00:00:00Z",
                "2020-05-20T00:00:00Z",
                "2020-06-20T00:00:00Z",
                "2020-07-09T00:00:00Z",
                "2020-07-28T00:00:00Z",
                "2020-08-18T00:00:00Z",
                "2020-09-08T00:00:00Z",
                "2020-10-05T00:00:00Z"
              ]
            }
          ]
        },
        {
          "regularPrice": 500,
          "finalPrice": 500,
          "bundle": null,
          "banner": null,
          "giftable": true,
          "refundable": true,
          "sortPriority": -4,
          "categories": [
            "Daily 4"
          ],
          "devName": "[VIRTUAL]1 x Bionic Synapse for 500 MtxCurrency",
          "offerId": "v2:/b41257b23cb2348fcf6133474fb1d8764f11219def790d31217950aaeceda925",
          "displayAssetPath": "FortniteGame/Content/Catalog/DisplayAssets/DA_Featured_Pickaxe_ID_383_HandymanMale",
          "newDisplayAssetPath": "FortniteGame/Content/Catalog/NewDisplayAssets/DAv2_Pickaxe_ID_383_HandymanMale",
          "items": [
            {
              "id": "Pickaxe_ID_383_HandymanMale",
              "name": "Bionic Synapse",
              "description": "Built for you and you alone.",
              "type": {
                "value": "pickaxe",
                "displayValue": "Harvesting Tool",
                "backendValue": "AthenaPickaxe"
              },
              "rarity": {
                "value": "uncommon",
                "displayValue": "Uncommon",
                "backendValue": "EFortRarity::Uncommon"
              },
              "series": null,
              "set": {
                "value": "Revenge Redux",
                "text": "Part of the Revenge Redux set.",
                "backendValue": "RepaymentUpdate"
              },
              "introduction": {
                "chapter": "2",
                "season": "2",
                "text": "Introduced in Chapter 2, Season 2.",
                "backendValue": 12
              },
              "images": {
                "smallIcon": "https://fortnite-api.com/images/cosmetics/br/pickaxe_id_383_handymanmale/smallicon.png",
                "icon": "https://fortnite-api.com/images/cosmetics/br/pickaxe_id_383_handymanmale/icon.png",
                "featured": "https://fortnite-api.com/images/cosmetics/br/pickaxe_id_383_handymanmale/featured.png",
                "other": null
              },
              "variants": null,
              "gameplayTags": [
                "Cosmetics.Filter.Season.12",
                "Cosmetics.Source.ItemShop",
                "Cosmetics.Set.RepaymentUpdate"
              ],
              "showcaseVideo": "Hu84yXUPoFI",
              "displayAssetPath": "FortniteGame/Content/Catalog/DisplayAssets/DA_Featured_Pickaxe_ID_383_HandymanMale",
              "definitionPath": "FortniteGame/Content/Athena/Items/Weapons/WID_Harvest_Pickaxe_HandymanMale",
              "path": "FortniteGame/Content/Athena/Items/Cosmetics/Pickaxes/Pickaxe_ID_383_HandymanMale",
              "added": "2020-03-31T06:11:29Z",
              "shopHistory": [
                "2020-04-07T00:00:00Z",
                "2020-05-27T08:00:00Z",
                "2020-07-03T00:00:00Z",
                "2020-08-05T00:00:00Z",
                "2020-09-12T00:00:00Z",
                "2020-10-05T00:00:00Z"
              ]
            }
          ]
        },
        {
          "regularPrice": 200,
          "finalPrice": 200,
          "bundle": null,
          "banner": null,
          "giftable": true,
          "refundable": true,
          "sortPriority": -6,
          "categories": [
            "Daily 6"
          ],
          "devName": "[VIRTUAL]1 x Finger Wag for 200 MtxCurrency",
          "offerId": "v2:/46960c7c54ec34dd996cbe48a5034d9f4abe3753717ebe6e6cb812eb09809ebc",
          "displayAssetPath": null,
          "newDisplayAssetPath": "FortniteGame/Content/Catalog/NewDisplayAssets/DAv2_EID_NotToday",
          "items": [
            {
              "id": "EID_NotToday",
              "name": "Finger Wag",
              "description": "Not today, my friend.",
              "type": {
                "value": "emote",
                "displayValue": "Emote",
                "backendValue": "AthenaDance"
              },
              "rarity": {
                "value": "uncommon",
                "displayValue": "Uncommon",
                "backendValue": "EFortRarity::Uncommon"
              },
              "series": null,
              "set": null,
              "introduction": {
                "chapter": "1",
                "season": "5",
                "text": "Introduced in Chapter 1, Season 5.",
                "backendValue": 5
              },
              "images": {
                "smallIcon": "https://fortnite-api.com/images/cosmetics/br/eid_nottoday/smallicon.png",
                "icon": "https://fortnite-api.com/images/cosmetics/br/eid_nottoday/icon.png",
                "featured": null,
                "other": null
              },
              "variants": null,
              "gameplayTags": [
                "Cosmetics.EmoteType.Dance",
                "Cosmetics.Source.ItemShop",
                "Phoebe.Cosmetic.Minus.Zone2",
                "Phoebe.Cosmetic.Minus.Zone1",
                "Cosmetics.Filter.Season.5"
              ],
              "showcaseVideo": "oazT6lMcEx4",
              "displayAssetPath": null,
              "definitionPath": null,
              "path": "FortniteGame/Content/Athena/Items/Cosmetics/Dances/EID_NotToday",
              "added": "2019-11-20T12:49:42Z",
              "shopHistory": [
                "2018-07-28T00:00:00Z",
                "2018-08-27T00:00:00Z",
                "2018-11-09T00:00:00Z",
                "2018-12-07T00:00:00Z",
                "2019-10-17T00:00:00Z",
                "2020-01-16T00:00:00Z",
                "2020-03-18T00:00:00Z",
                "2020-04-25T00:00:00Z",
                "2020-05-29T00:00:00Z",
                "2020-07-03T00:00:00Z",
                "2020-07-28T00:00:00Z",
                "2020-09-15T00:00:00Z",
                "2020-10-05T00:00:00Z"
              ]
            }
          ]
        }
      ]
    },
    "votes": null,
    "voteWinners": null
  }
}